LICENSE.txt
MANIFEST.in
README.md
VERSION
setup.py
PyBuddy.egg-info/PKG-INFO
PyBuddy.egg-info/SOURCES.txt
PyBuddy.egg-info/dependency_links.txt
PyBuddy.egg-info/entry_points.txt
PyBuddy.egg-info/top_level.txt
pybuddy/__init__.py
pybuddy/cli.py
pybuddy/config.py
pybuddy/constants.py
pybuddy/create.py
pybuddy/git.py
pybuddy/playground.py
pybuddy/pybuddy.ini
pybuddy/utils.py
pybuddy/virtualenv.py
pybuddy/data/pybuddy.ini
pybuddy/templates/MANIFEST.in.tpl
pybuddy/templates/README.md.tpl
pybuddy/templates/VERSION.tpl
pybuddy/templates/__init__.py.tpl
pybuddy/templates/gitignore.tpl
pybuddy/templates/module.py.tpl
pybuddy/templates/pytest.ini.tpl
pybuddy/templates/setup.cfg.tpl
pybuddy/templates/setup.py.tpl
pybuddy/templates/test_module.py.tpl
pybuddy/templates/licenses/AGPLv3.tpl
pybuddy/templates/licenses/Apache20.tpl
pybuddy/templates/licenses/Empty.tpl
pybuddy/templates/licenses/GPLv3.tpl
pybuddy/templates/licenses/LGPLv3.tpl
pybuddy/templates/licenses/MIT.tpl
pybuddy/templates/licenses/Mozilla20.tpl
pybuddy/templates/licenses/Unlicense.tpl
tests/test_create.py