Metadata-Version: 1.0
Name: PyBuddy
Version: 0.1.4
Summary: Creates and setups a well structured Python project
Home-page: https://github.com/TiagoBras/PyBuddy
Author: Tiago Bras
Author-email: tiagodsbras@gmail.com
License: MIT
Platform: UNKNOWN
